smn/__init__.py
smn/cli.py
smn/context.py
smn/runners.py
smn/utils.py
summoner_cli-0.0.5.dist-info/METADATA
summoner_cli-0.0.5.dist-info/WHEEL
summoner_cli-0.0.5.dist-info/entry_points.txt
summoner_cli-0.0.5.dist-info/licenses/LICENSE
summoner_cli-0.0.5.dist-info/RECORD
