Metadata-Version: 2.4
Name: summoner-cli
Version: 0.0.5
Summary: a macro command runner
Project-URL: Repository, https://github.com/adammillerio/smn
Author-email: Adam Miller <miller@adammiller.io>
License-File: LICENSE
Classifier: Development Status :: 3 - Alpha
Classifier: Intended Audience :: Developers
Classifier: License :: OSI Approved :: MIT License
Classifier: Programming Language :: Python :: 3
Classifier: Programming Language :: Python :: 3 :: Only
Classifier: Programming Language :: Python :: 3.10
Classifier: Programming Language :: Python :: 3.11
Classifier: Programming Language :: Python :: 3.12
Requires-Python: >=3.10
Requires-Dist: click-tree>=0.0.1
Requires-Dist: click>=8.1.8
Requires-Dist: fabric2>=3.2.2
Requires-Dist: invoke>=2.2.0
Requires-Dist: pyre-extensions>=0.0.32
